{
  "version": "1.1.0",
  "versionCode": 8,
  "releaseDate": "2026-02-11",
  "downloadUrl": "https://github.com/HFZY-Developments/khair_ul_madaaris_library/releases/download/v1.1.0/app-release.apk",
  "fileSize": "72.8 MB",
  "mandatory": true,
  "changelog": [
    "Fixed overdue return glitch in scanner flow",
    "Improved scanner dialog stability and route handling",
    "Prevented wrong-row updates in Google Sheets sync",
    "Added strict APK integrity verification before install",
    "Refined premium visuals on Home, Scanner, and Update dialog"
  ],
  "minAndroidVersion": 21,
  "sha256": "aa845bad38d70003db8f967e3e042e4efa2d5782633f49138077118af4530fec"
}
